dita/__init__.py
dita/cleanup/__init__.py
dita/cleanup/__main__.py
dita/cleanup/cli.py
dita/cleanup/out.py
dita/cleanup/xml.py
dita_cleanup-0.9.4.dist-info/licenses/LICENSE
dita_cleanup-0.9.4.dist-info/METADATA
dita_cleanup-0.9.4.dist-info/WHEEL
dita_cleanup-0.9.4.dist-info/entry_points.txt
dita_cleanup-0.9.4.dist-info/top_level.txt
dita_cleanup-0.9.4.dist-info/RECORD
