Metadata-Version: 2.4
Name: dita-cleanup
Version: 0.9.4
Summary: Clean up DITA topics after conversion from AsciiDoc.
Author-email: Jaromir Hradilek <jhradilek@gmail.com>
License-Expression: MIT
Project-URL: Homepage, https://github.com/jhradilek/fix-dita-links
Project-URL: Repository, https://github.com/jhradilek/fix-dita-links
Project-URL: Issues, https://github.com/jhradilek/fix-dita-links/issues
Classifier: Programming Language :: Python :: 3
Classifier: Operating System :: OS Independent
Classifier: Development Status :: 4 - Beta
Classifier: Environment :: Console
Classifier: Intended Audience :: Developers
Classifier: Topic :: Documentation
Requires-Python: >=3.12
License-File: LICENSE
Requires-Dist: lxml>=4.9.2
Dynamic: license-file
